<function-spec name="cons">
  <syntax>(cons obj1 obj2)</syntax>

  <description><p>Constructs a new cons cell with car
  <paramname>obj1</paramname> and cdr
  <paramname>obj2</paramname>.</p></description>

  <parameters>
    <parameter name="obj1">The car of the newly constructed cons cell will be set to this object</parameter>
    <parameter name="obj2">The cdr of the newly constructed cons cell will be set to this object</parameter>
  </parameters>
  <examples>
    <example expr="(cons 'a 'b)" value="(a . b)"/>
    <example expr="(cons 'a nil)" value="(a)"/>
    <example expr="(cons 'a '(b c d))" value="(a b c d)"/>
  </examples>
</function-spec>
